README.rst
setup.py
snot/__init__.py
snot/_nose.py
snot/_pytest.py
snot.egg-info/PKG-INFO
snot.egg-info/SOURCES.txt
snot.egg-info/dependency_links.txt
snot.egg-info/entry_points.txt
snot.egg-info/top_level.txt