Metadata-Version: 1.0
Name: snot
Version: 1.0.0
Summary: Snot is colored output from nose. Or, um, py.test.
Home-page: https://github.com/whit537/snot
Author: Chad Whitacre
Author-email: chad@zetaweb.com
License: UNKNOWN
Platform: UNKNOWN
